{
  "retracted": false,
  "timestamp": 1560556800000,
  "updates": [
    {
      "timestamp": 1586887464789,
      "identifier": {
        "doi": "10.1016/j.jad.2019.01.009"
      },
      "type": "erratum"
    }
  ],
  "identifier": {
    "doi": "10.1016/j.jad.2018.04.111"
  },
  "publisher": "Elsevier BV",
  "title": "Corrigendum to “Comparison of comorbid depression between irritable bowel syndrome and inflammatory bowel disease: A meta-analysis of comparative studies” [J Affect Disord. 2018 237: 37–46. doi: 10.1016/j.jad.2018.04.111.]"
}
