{
  "retracted": false,
  "timestamp": 1403913600000,
  "updates": [
    {
      "timestamp": 1586457077329,
      "identifier": {
        "doi": "10.1007/s00217-014-2267-z"
      },
      "type": "correction"
    }
  ],
  "identifier": {
    "doi": "10.1007/s00217-014-2232-x"
  },
  "publisher": "Springer Science and Business Media LLC",
  "title": "Erratum to: Development of suitable standards for quantitative determination of persimmon phenol contents in Folin-Ciocalteu and vanillin assays"
}
