{
  "retracted": false,
  "timestamp": 1561420800000,
  "updates": [
    {
      "timestamp": 1564054832434,
      "identifier": {
        "doi": "10.1039/c9py90101a"
      },
      "type": "correction"
    }
  ],
  "identifier": {
    "doi": "10.1039/c9py00458k"
  },
  "journal": "Polymer Chemistry",
  "publisher": "Royal Society of Chemistry (RSC)",
  "title": "Correction: Synthesis and solution behaviour of dual light- and temperature-responsive poly(triethylene glycol-co-spiropyran) copolymers and block copolymers"
}
