{
  "retracted": false,
  "timestamp": 1587686400000,
  "updates": [
    {
      "timestamp": 1589179221902,
      "identifier": {
        "doi": "10.3349/ymj.2020.61.5.445"
      },
      "type": "erratum"
    }
  ],
  "identifier": {
    "doi": "10.3349/ymj.2019.60.10.935"
  },
  "journal": "Yonsei Medical Journal",
  "publisher": "Yonsei University College of Medicine (KAMJE)",
  "title": "Erratum to “Distinct Neural Correlates of Executive Function by Amyloid Positivity and Associations with Clinical Progression in Mild Cognitive Impairment” by Yoon HJ, et al. (Yonsei Med J 2019;60(10):935–943.)"
}
