{
  "retracted": false,
  "timestamp": 1388361600000,
  "updates": [
    {
      "timestamp": 1588832690988,
      "identifier": {
        "doi": "10.1371/annotation/f5414425-512f-4832-9166-3a6132ccd068"
      },
      "type": "correction"
    }
  ],
  "identifier": {
    "doi": "10.1371/journal.pone.0078218"
  },
  "publisher": "Public Library of Science (PLoS)",
  "title": "Correction: Catheter-Based Renal Sympathetic Denervation Significantly Inhibits Atrial Fibrillation Induced by Electrical Stimulation of the Left Stellate Ganglion and Rapid Atrial Pacing"
}
