{
  "retracted": true,
  "timestamp": 1562198400000,
  "updates": [
    {
      "timestamp": 1585236022061,
      "identifier": {
        "doi": "10.1007/s40290-019-00293-0"
      },
      "type": "retraction"
    }
  ],
  "identifier": {
    "doi": "10.1007/s40290-019-00268-1"
  },
  "publisher": "Springer Science and Business Media LLC",
  "title": "Retraction Note to: The Longitudinal Incidence of Human Papillomavirus Vaccination in Spanish Primary Care in the First 6 Years After Approval"
}
