{
  "retracted": false,
  "timestamp": 1516665600000,
  "updates": [
    {
      "timestamp": 1574788440774,
      "identifier": {
        "doi": "10.1039/c8nr90017e"
      },
      "type": "correction"
    }
  ],
  "identifier": {
    "doi": "10.1039/c5nr05332c"
  },
  "journal": "Nanoscale",
  "publisher": "Royal Society of Chemistry (RSC)",
  "title": "Correction: TiO2/vanadate (Sr10V6O25, Ni3V2O8, Zn2V2O7) heterostructured photocatalysts with enhanced photocatalytic activity for photoreduction of CO2 into CH4"
}
