{
  "retracted": false,
  "timestamp": 1580515200000,
  "updates": [
    {
      "timestamp": 1591736957060,
      "identifier": {
        "doi": "10.1007/s00227-020-3651-9"
      },
      "type": "correction"
    }
  ],
  "identifier": {
    "doi": "10.1007/s00227-019-3609-y"
  },
  "journal": "Marine Biology",
  "publisher": "Springer Science and Business Media LLC",
  "title": "Correction to: Multiple zooplankton species alter the stoichiometric interactions between producer and consumer levels"
}
