{
  "retracted": false,
  "timestamp": 1459468800000,
  "updates": [
    {
      "timestamp": 1557272506550,
      "identifier": {
        "doi": "10.1016/j.cpr.2016.02.003"
      },
      "type": "erratum"
    }
  ],
  "identifier": {
    "doi": "10.1016/j.cpr.2015.04.001"
  },
  "publisher": "Elsevier BV",
  "title": "Erratum to “The puzzle of intrafamilial child sexual abuse: A meta-analysis comparing intrafamilial and extrafamilial offenders with child victims” [Clin. Psychol. Rev. 39 (2015) 42–57]"
}
