{
  "retracted": false,
  "timestamp": 1583020800000,
  "updates": [
    {
      "timestamp": 1591695072511,
      "identifier": {
        "doi": "10.1016/j.apsoil.2019.103446"
      },
      "type": "erratum"
    }
  ],
  "identifier": {
    "doi": "10.1016/j.apsoil.2012.04.006"
  },
  "journal": "Applied Soil Ecology",
  "publisher": "Elsevier BV",
  "title": "Corrigendum to “Structure, functions and interguild relationships of the soil nematode assemblage in organic vegetable production” [Appl. Soil Ecol. 6 (2012)16–25]"
}
