{
  "retracted": false,
  "timestamp": 1524700800000,
  "updates": [
    {
      "timestamp": 1574827521048,
      "identifier": {
        "doi": "10.1038/s41598-018-23185-w"
      },
      "type": "correction"
    }
  ],
  "identifier": {
    "doi": "10.1038/s41598-017-11868-9"
  },
  "journal": "Scientific Reports",
  "publisher": "Springer Science and Business Media LLC",
  "title": "Publisher Correction: A new antagonist for CCR4 attenuates allergic lung inflammation in a mouse model of asthma"
}
