{
  "retracted": false,
  "timestamp": 1500336000000,
  "updates": [
    {
      "timestamp": 1585437425730,
      "identifier": {
        "doi": "10.1007/s11240-017-1269-5"
      },
      "type": "erratum"
    }
  ],
  "identifier": {
    "doi": "10.1007/s11240-017-1171-1"
  },
  "publisher": "Springer Science and Business Media LLC",
  "title": "Erratum to: Overexpression of the gibberellin 20-oxidase gene from Torenia fournieri resulted in modified trichome formation and terpenoid of metabolites Artemisia annua L."
}
