{
  "retracted": false,
  "timestamp": 1560729600000,
  "updates": [
    {
      "timestamp": 1590965045010,
      "identifier": {
        "doi": "10.7567/1347-4065/ab26a6"
      },
      "type": "correction"
    }
  ],
  "identifier": {
    "doi": "10.7567/1347-4065/ab0f17"
  },
  "publisher": "IOP Publishing",
  "title": "Corrigendum: “Influence of surface nitridation and an AlN buffer layer on the growth of GaN nanostructures on a flexible Ti metal foil using laser molecular beam epitaxy” [Jpn. J. Appl. Phys. 58, SC1032 (2019)]"
}
