{
  "retracted": false,
  "timestamp": 1487289600000,
  "updates": [
    {
      "timestamp": 1495721001546,
      "identifier": {
        "doi": "10.1186/s13104-017-2419-x"
      },
      "type": "correction"
    }
  ],
  "identifier": {
    "doi": "10.1186/s13104-015-1398-z"
  },
  "publisher": "Springer Nature",
  "title": "Erratum to: Cause-effect relations between 55 kD soluble TNF receptor concentrations and specific and unspecific symptoms in a patient with mild SLE disease activity: an exploratory time series analysis study"
}
