{
  "retracted": false,
  "timestamp": 1551744000000,
  "updates": [
    {
      "timestamp": 1588970584360,
      "identifier": {
        "doi": "10.1371/journal.pone.0213612"
      },
      "type": "correction"
    }
  ],
  "identifier": {
    "doi": "10.1371/journal.pone.0209357"
  },
  "publisher": "Public Library of Science (PLoS)",
  "title": "Correction: Phenotypic and genomic analyses of bacteriophages targeting environmental and clinical CS3-expressing enterotoxigenic Escherichia coli (ETEC) strains"
}
