{
  "retracted": false,
  "timestamp": 1485216000000,
  "updates": [
    {
      "timestamp": 1495678320980,
      "identifier": {
        "doi": "10.1007/s10529-017-2287-4"
      },
      "type": "correction"
    }
  ],
  "identifier": {
    "doi": "10.1007/s10529-016-2192-2"
  },
  "journal": "Biotechnology Letters",
  "publisher": "Springer Nature",
  "title": "Erratum to: The use of natural infochemicals for sustainable and efficient harvesting of the microalgae Scenedesmus spp. for biotechnology: insights from a meta-analysis"
}
