{
  "retracted": false,
  "timestamp": 1314144000000,
  "updates": [
    {
      "timestamp": 1570797606878,
      "identifier": {
        "doi": "10.1007/s00411-011-0378-5"
      },
      "type": "erratum"
    }
  ],
  "identifier": {
    "doi": "10.1007/s00411-009-0231-2"
  },
  "journal": "Radiation and Environmental Biophysics",
  "publisher": "Springer Science and Business Media LLC",
  "title": "Erratum to: A new view of radiation-induced cancer: integrating short- and long-term processes. Parts I and II"
}
