{
  "retracted": false,
  "timestamp": 1428624000000,
  "updates": [
    {
      "timestamp": 1496056817510,
      "identifier": {
        "doi": "10.1371/journal.pgen.1005132"
      },
      "type": "correction"
    }
  ],
  "identifier": {
    "doi": "10.1371/journal.pgen.1004400"
  },
  "publisher": "Public Library of Science (PLoS)",
  "title": "Correction: JNK Controls the Onset of Mitosis in Planarian Stem Cells and Triggers Apoptotic Cell Death Required for Regeneration and Remodeling"
}
