{
  "retracted": false,
  "timestamp": 1487116800000,
  "updates": [
    {
      "timestamp": 1495650892474,
      "identifier": {
        "doi": "10.1016/j.optcom.2016.10.026"
      },
      "type": "err"
    }
  ],
  "identifier": {
    "doi": "10.1016/j.optcom.2014.10.050"
  },
  "journal": "Optics Communications",
  "publisher": "Elsevier BV",
  "title": "Corrigendum to “Correlated-imaging-based chosen plaintext attack on general cryptosystems composed of linear canonical transforms and phase encodings” [Opt. Commun. 338 (2015) 164–167]"
}
