{
  "retracted": false,
  "timestamp": 1567555200000,
  "updates": [
    {
      "timestamp": 1567579356739,
      "identifier": {
        "doi": "10.1007/s10985-019-09484-y"
      },
      "type": "correction"
    }
  ],
  "identifier": {
    "doi": "10.1007/s10985-018-9428-5"
  },
  "journal": "Lifetime Data Analysis",
  "publisher": "Springer Science and Business Media LLC",
  "title": "Correction to: Improved precision in the analysis of randomized trials with survival outcomes, without assuming proportional hazards"
}
