{
  "retracted": false,
  "timestamp": 1459468800000,
  "updates": [
    {
      "timestamp": 1585707033137,
      "identifier": {
        "doi": "10.1016/j.kint.2016.01.006"
      },
      "type": "erratum"
    }
  ],
  "identifier": {
    "doi": "10.1038/ki.2014.110"
  },
  "publisher": "Elsevier BV",
  "title": "Scialla JJ, Liu J, Crews DC, et al. An instrumental variable approach finds no associated harm or benefit with early dialysis initiation in the United States. Kidney Int. 2014;86:798–809"
}
