{
  "retracted": false,
  "timestamp": 1559001600000,
  "updates": [
    {
      "timestamp": 1559065441495,
      "identifier": {
        "doi": "10.1371/journal.pcbi.1007062"
      },
      "type": "correction"
    }
  ],
  "identifier": {
    "doi": "10.1371/journal.pcbi.1006211"
  },
  "journal": "PLOS Computational Biology",
  "publisher": "Public Library of Science (PLoS)",
  "title": "Correction: Accounting for non-stationarity in epidemiology by embedding time-varying parameters in stochastic models"
}
