{
  "retracted": false,
  "timestamp": 1580256000000,
  "updates": [
    {
      "timestamp": 1591735141902,
      "identifier": {
        "doi": "10.1177/1089253220904808"
      },
      "type": "correction"
    }
  ],
  "identifier": {
    "doi": "10.1177/1089253219870628"
  },
  "journal": "Seminars in Cardiothoracic and Vascular Anesthesia",
  "publisher": "SAGE Publications",
  "title": "Corrigendum to “Deep Tracheal Extubation Using Dexmedetomidine in Children With Congenital Heart Disease Undergoing Cardiac Catheterization: Advantages and Complications”"
}
