{"retracted":false,"update":{"timestamp":1410393600000,"doi":"10.1016/j.nima.2014.03.036","type":"err"},"doi":"10.1016/j.nima.2014.01.019","journal":"Nuclear Instruments and Methods in Physics Research Section A: Accelerators, Spectrometers, Detectors and Associated Equipment","publisher":"Elsevier BV","title":"Corrigendum to “Landau damping and the head–tail instability of the coupled synchro-betatron coherent oscillations” [Nuclear Instruments and Methods in Physics Research A 743 (2014) 51–55]"}
