{
  "retracted": false,
  "timestamp": 1569369600000,
  "updates": [
    {
      "timestamp": 1573537287440,
      "identifier": {
        "doi": "10.1111/mmi.14343"
      },
      "type": "correction"
    }
  ],
  "identifier": {
    "doi": "10.1111/mmi.13965"
  },
  "journal": "Molecular Microbiology",
  "publisher": "Wiley",
  "title": "The distinct PhoPR mediated responses to phosphate limitation in\n            Bacillus subtilis\n            subspecies\n            subtilis\n            and\n            spizizenii\n            stem from differences in wall teichoic acid composition and metabolism"
}
