{
  "retracted": false,
  "timestamp": 1541203200000,
  "updates": [
    {
      "timestamp": 1572741649143,
      "identifier": {
        "doi": "10.1007/s12549-018-0364-x"
      },
      "type": "correction"
    }
  ],
  "identifier": {
    "doi": "10.1007/s12549-018-0340-5"
  },
  "journal": "Palaeobiodiversity and Palaeoenvironments",
  "publisher": "Springer Science and Business Media LLC",
  "title": "Correction to: Late Silurian and Devonian ostracods of the Istanbul Zone (Western Pontides) and the Taurides: palaeogeographical implications"
}
