{
  "retracted": false,
  "timestamp": 1509494400000,
  "updates": [
    {
      "timestamp": 1557256354046,
      "identifier": {
        "doi": "10.1016/j.jnt.2017.03.023"
      },
      "type": "erratum"
    }
  ],
  "identifier": {
    "doi": "10.1016/j.jnt.2016.09.030"
  },
  "journal": "Journal of Number Theory",
  "publisher": "Elsevier BV",
  "title": "Corrigendum to “Some real quadratic number fields with their Hilbert 2-class field having cyclic 2-class group” [J. Number Theory 173 (2017) 529–546]"
}
