{
  "retracted": false,
  "timestamp": 1372636800000,
  "updates": [
    {
      "timestamp": 1496012936409,
      "identifier": {
        "doi": "10.1016/j.jbusvent.2013.02.005"
      },
      "type": "err"
    }
  ],
  "identifier": {
    "doi": "10.1016/j.jbusvent.2007.06.002"
  },
  "journal": "Journal of Business Venturing",
  "publisher": "Elsevier BV",
  "title": "Retraction notice to “Externally commercializing technology assets: An examination of different process stages” [J. Bus. Venturing 23/4 (2008) 445–464]"
}
