{
  "retracted": false,
  "timestamp": 1554076800000,
  "updates": [
    {
      "timestamp": 1565151110858,
      "identifier": {
        "doi": "10.1016/j.optmat.2019.04.025"
      },
      "type": "erratum"
    }
  ],
  "identifier": {
    "doi": "10.1016/j.optmat.2017.12.034"
  },
  "journal": "Optical Materials",
  "publisher": "Elsevier BV",
  "title": "Corrigendum to “Influence of functional groups on the photophysical properties of dimethylamino chalcones as laser dyes” [Optical Mat. 76 (2018) 216–221]"
}
