{
  "retracted": false,
  "timestamp": 1538611200000,
  "updates": [
    {
      "timestamp": 1570146068257,
      "identifier": {
        "doi": "10.1038/s41565-018-0293-x"
      },
      "type": "correction"
    }
  ],
  "identifier": {
    "doi": "10.1038/s41565-018-0183-2"
  },
  "journal": "Nature Nanotechnology",
  "publisher": "Springer Science and Business Media LLC",
  "title": "Author Correction: Non-flammable electrolyte enables Li-metal batteries with aggressive cathode chemistries"
}
