{
  "retracted": false,
  "timestamp": 1596067200000,
  "updates": [
    {
      "timestamp": 1591834230979,
      "identifier": {
        "doi": "10.1016/j.jprot.2020.103828"
      },
      "type": "erratum"
    }
  ],
  "identifier": {
    "doi": "10.1016/j.jprot.2020.103796"
  },
  "journal": "Journal of Proteomics",
  "publisher": "Elsevier BV",
  "title": "Corrigendum to proteomic analysis detects deregulated reverse cholesterol transport in human subjects with ST-segment elevation myocardial infarction"
}
