{
  "retracted": false,
  "timestamp": 1577836800000,
  "updates": [
    {
      "timestamp": 1591713553855,
      "identifier": {
        "doi": "10.1144/jgs2019-205"
      },
      "type": "correction"
    }
  ],
  "identifier": {
    "doi": "10.1144/jgs2018-075"
  },
  "journal": "Journal of the Geological Society",
  "publisher": "Geological Society of London",
  "title": "Erratum for ‘Devonian (c. 388–375 Ma) Horn River Group of Mackenzie Platform (NW Canada) is an open-shelf succession recording oceanic anoxic events’, Journal of the Geological Society, London, 176, 29-45"
}
