{
  "retracted": false,
  "timestamp": 1382486400000,
  "updates": [
    {
      "timestamp": 1496056486228,
      "identifier": {
        "doi": "10.1371/annotation/e8b7df48-4639-4ac1-8a98-cb13dea3415b"
      },
      "type": "correction"
    }
  ],
  "identifier": {
    "doi": "10.1371/journal.pcbi.1003259"
  },
  "publisher": "Public Library of Science (PLoS)",
  "title": "Correction: A Simple Rule for Dendritic Spine and Axonal Bouton Formation Can Account for Cortical Reorganization after Focal Retinal Lesions"
}
