{
  "retracted": false,
  "timestamp": 1519084800000,
  "updates": [
    {
      "timestamp": 1574800267516,
      "identifier": {
        "doi": "10.1016/j.immuni.2018.01.010"
      },
      "type": "erratum"
    }
  ],
  "identifier": {
    "doi": "10.1016/j.immuni.2017.12.007"
  },
  "journal": "Immunity",
  "publisher": "Elsevier BV",
  "title": "NKp46 Receptor-Mediated Interferon-γ Production by Natural Killer Cells Increases Fibronectin 1 to Alter Tumor Architecture and Control Metastasis"
}
