{
  "retracted": false,
  "timestamp": 1501632000000,
  "updates": [
    {
      "timestamp": 1550479748166,
      "identifier": {
        "doi": "10.1007/s40520-017-0801-0"
      },
      "type": "erratum"
    }
  ],
  "identifier": {
    "doi": "10.1007/s40520-017-0768-x"
  },
  "journal": "Aging Clinical and Experimental Research",
  "publisher": "Springer Nature",
  "title": "Erratum to: The impact of leisure on mental health of Sardinian elderly from the ‘blue zone’: evidence for ageing well"
}
