{
  "retracted": false,
  "timestamp": 1500336000000,
  "updates": [
    {
      "timestamp": 1585437847406,
      "identifier": {
        "doi": "10.1080/09637486.2017.1346897"
      },
      "type": "correction"
    }
  ],
  "identifier": {
    "doi": "10.1080/09637486.2017.1336515"
  },
  "publisher": "Informa UK Limited",
  "title": "Correction to: Vitale, Bianchi, Rapetti, Pepe, Giacco, Giacco and Riccardi, A nutritional intervention programme at a worksite canteen to promote a healthful inspired by the traditional Mediterranean diet"
}
