{
  "retracted": false,
  "timestamp": 1447027200000,
  "updates": [
    {
      "timestamp": 1586639810273,
      "identifier": {
        "doi": "10.1007/s13239-015-0248-4"
      },
      "type": "correction"
    }
  ],
  "identifier": {
    "doi": "10.1007/s13239-015-0212-3"
  },
  "publisher": "Springer Science and Business Media LLC",
  "title": "Erratum to: Pulmonary Hemodynamics Simulations Before Stage 2 Single Ventricle Surgery: Patient-Specific Parameter Identification and Clinical Data Assessment"
}
