{
  "retracted": false,
  "timestamp": 1584662400000,
  "updates": [
    {
      "timestamp": 1591768449925,
      "identifier": {
        "doi": "10.1038/s41598-020-62303-5"
      },
      "type": "correction"
    }
  ],
  "identifier": {
    "doi": "10.1038/s41598-020-60048-9"
  },
  "journal": "Scientific Reports",
  "publisher": "Springer Science and Business Media LLC",
  "title": "Publisher Correction: Specific memory B cell response in humans upon infection with highly pathogenic H7N7 avian influenza virus"
}
