{
  "retracted": false,
  "timestamp": 1520899200000,
  "updates": [
    {
      "timestamp": 1573938617924,
      "identifier": {
        "doi": "10.1182/bloodadvances.2018017491"
      },
      "type": "erratum"
    }
  ],
  "identifier": {
    "doi": "10.1182/bloodadvances.2017011411"
  },
  "journal": "Blood Advances",
  "publisher": "American Society of Hematology",
  "title": "Francica JR, Zak DE, Linde C, et al. Innate transcriptional effects by adjuvants on the magnitude, quality, and durability of HIV envelope responses in NHPs. Blood Adv. 2017;1(25):2329-2342."
}
