{
  "retracted": false,
  "timestamp": 1582070400000,
  "updates": [
    {
      "timestamp": 1590230419231,
      "identifier": {
        "doi": "10.1007/s11869-020-00793-y"
      },
      "type": "correction"
    }
  ],
  "identifier": {
    "doi": "10.1007/s11869-019-00725-5"
  },
  "journal": "Air Quality, Atmosphere & Health",
  "publisher": "Springer Science and Business Media LLC",
  "title": "Correction to: A conceptual model to understand the soluble and insoluble Cr species in deliquesced particles"
}
