{
  "retracted": false,
  "timestamp": 1504224000000,
  "updates": [
    {
      "timestamp": 1557249093168,
      "identifier": {
        "doi": "10.1016/j.ihj.2017.08.024"
      },
      "type": "erratum"
    }
  ],
  "identifier": {
    "doi": "10.1016/j.ihj.2016.01.014"
  },
  "journal": "Indian Heart Journal",
  "publisher": "Elsevier BV",
  "title": "Corrigendum to “Administration of low molecular weight and unfractionated heparin during percutaneous coronary intervention” [Indian Heart J. 68 (2) (2016) 213–224]"
}
