{
  "retracted": false,
  "timestamp": 1508889600000,
  "updates": [
    {
      "timestamp": 1556701954544,
      "identifier": {
        "doi": "10.1080/10717544.2017.1394511"
      },
      "type": "correction"
    }
  ],
  "identifier": {
    "doi": "10.1080/10717544.2017.1373165"
  },
  "journal": "Drug Delivery",
  "publisher": "Informa UK Limited",
  "title": "Correction to: Dong et al., Promising galactose-decorated biodegradable poloxamer 188-PLGA diblock copolymer nanoparticles of resibufogenin for enhancing liver cancer therapy"
}
