{
  "retracted": false,
  "timestamp": 1553212800000,
  "updates": [
    {
      "timestamp": 1590824526322,
      "identifier": {
        "doi": "10.1007/978-3-319-75913-5_30"
      },
      "type": "correction"
    }
  ],
  "identifier": {
    "doi": "10.1007/978-3-319-75913-5_13"
  },
  "publisher": "Springer International Publishing",
  "title": "Correction to: The Impact of Age and Entrepreneurial Age-Based Self-Image on Entrepreneurial Competencies of Male and Female: Evidence of GEM-Iran 2016 Data"
}
