{
  "retracted": false,
  "timestamp": 1526428800000,
  "updates": [
    {
      "timestamp": 1574835543167,
      "identifier": {
        "doi": "10.1371/journal.pone.0197707"
      },
      "type": "correction"
    }
  ],
  "identifier": {
    "doi": "10.1371/journal.pone.0129551"
  },
  "publisher": "Public Library of Science (PLoS)",
  "title": "Correction: A New Method for Estimating the Number of Undiagnosed HIV Infected Based on HIV Testing History, with an Application to Men Who Have Sex with Men in Seattle/King County, WA"
}
