{
  "retracted": false,
  "timestamp": 1567296000000,
  "updates": [
    {
      "timestamp": 1586919090761,
      "identifier": {
        "doi": "10.1016/j.epsr.2019.04.009"
      },
      "type": "erratum"
    }
  ],
  "identifier": {
    "doi": "10.1016/j.epsr.2016.09.020"
  },
  "publisher": "Elsevier BV",
  "title": "Corrigendum on “Performance analysis of diode-bridge-type non-superconducting fault current limiter in improving transient stability of DFIG based variable speed wind generator”, Electric Power Systems Research, Vol 143, pp 782-793, 2017, Elsevier"
}
