{
  "retracted": false,
  "timestamp": 1500249600000,
  "updates": [
    {
      "timestamp": 1550474247756,
      "identifier": {
        "doi": "10.1186/s12891-017-1661-7"
      },
      "type": "correction"
    }
  ],
  "identifier": {
    "doi": "10.1186/s12891-017-1526-0"
  },
  "journal": "BMC Musculoskeletal Disorders",
  "publisher": "Springer Nature",
  "title": "Erratum to: more complications in uncemented compared to cemented hemiarthroplasty for displaced femoral neck fractures: a randomized controlled trial of 201 patients, with one year follow-up"
}
