{
  "retracted": false,
  "timestamp": 1580256000000,
  "updates": [
    {
      "timestamp": 1591280731840,
      "identifier": {
        "doi": "10.3390/ijms21082915"
      },
      "type": "correction"
    }
  ],
  "identifier": {
    "doi": "10.3390/ijms21030876"
  },
  "journal": "International Journal of Molecular Sciences",
  "publisher": "MDPI AG",
  "title": "Correction: Qi, W., et al. (+)-Usnic Acid Induces ROS-Dependent Apoptosis via Inhibition of Mitochondria Respiratory Chain Complexes and Nrf2 Expression in Lung Squamous Cell Carcinoma. Int. J. Mol. Sci. 2020, 21, 876"
}
