{
  "retracted": false,
  "timestamp": 1504224000000,
  "updates": [
    {
      "timestamp": 1585458704284,
      "identifier": {
        "doi": "10.1016/j.enfcli.2017.08.002"
      },
      "type": "erratum"
    }
  ],
  "identifier": {
    "doi": "10.1016/j.enfcli.2017.06.001"
  },
  "publisher": "Elsevier BV",
  "title": "Fe de errores de «La etnicidad: un abordaje esencial en la mejora con equidad de la calidad de la atención y la seguridad del paciente» <[Enferm Clin. 27 (2017) 209-210]>"
}
