{
  "retracted": false,
  "timestamp": 1527033600000,
  "updates": [
    {
      "timestamp": 1574837689018,
      "identifier": {
        "doi": "10.1038/s41598-018-24985-w"
      },
      "type": "correction"
    }
  ],
  "identifier": {
    "doi": "10.1038/s41598-017-05998-3"
  },
  "journal": "Scientific Reports",
  "publisher": "Springer Science and Business Media LLC",
  "title": "Author Correction: Prediction of size-resolved number concentration of cloud condensation nuclei and long-term measurements of their activation characteristics"
}
