{
  "retracted": false,
  "timestamp": 1521676800000,
  "updates": [
    {
      "timestamp": 1574823222772,
      "identifier": {
        "doi": "10.3938/jkps.72.742"
      },
      "type": "erratum"
    }
  ],
  "identifier": {
    "doi": "10.3938/jkps.72.260"
  },
  "journal": "Journal of the Korean Physical Society",
  "publisher": "Korean Physical Society",
  "title": "Erratum: Dual roles of a flouride-doped SnO2/TiO2 bilayer based on inverse opal/nanoparticle structure for water oxidation"
}
