{
  "retracted": false,
  "timestamp": 1440028800000,
  "updates": [
    {
      "timestamp": 1496022713164,
      "identifier": {
        "doi": "10.1371/journal.pone.0136482"
      },
      "type": "correction"
    }
  ],
  "identifier": {
    "doi": "10.1371/journal.pone.0131103"
  },
  "publisher": "Public Library of Science (PLoS)",
  "title": "Correction: The Tinkerbell (Tink) Mutation Identifies the Dual-Specificity MAPK Phosphatase INDOLE-3-BUTYRIC ACID-RESPONSE5 (IBR5) as a Novel Regulator of Organ Size in Arabidopsis"
}
