{
  "retracted": false,
  "timestamp": 1453939200000,
  "updates": [
    {
      "timestamp": 1585056632529,
      "identifier": {
        "doi": "10.1017/s0031182018001610"
      },
      "type": "correction"
    }
  ],
  "identifier": {
    "doi": "10.1017/s003118201500181x"
  },
  "publisher": "Cambridge University Press (CUP)",
  "title": "Molecular and comparative morphological analysis of central European parasitic flatworms of the superfamily Brachylaimoidea Allison, 1943 (Trematoda: Plagiorchiida) – CORRIGENDUM"
}
