{
  "retracted": true,
  "timestamp": 1575158400000,
  "updates": [
    {
      "timestamp": 1591715251814,
      "identifier": {
        "doi": "10.1016/j.fshw.2019.11.003"
      },
      "type": "erratum"
    }
  ],
  "identifier": {
    "doi": "10.1016/j.fshw.2018.04.001"
  },
  "journal": "Food Science and Human Wellness",
  "publisher": "Elsevier BV",
  "title": "Retraction notice to “Linking gut microbiota to aging process: A new target for anti-aging” [Food Sci. Hum. Wellness 7 (2) (2018) 111–119]"
}
