{
  "retracted": false,
  "timestamp": 1471219200000,
  "updates": [
    {
      "timestamp": 1585102105747,
      "identifier": {
        "doi": "10.1016/j.ijcard.2016.04.159"
      },
      "type": "erratum"
    }
  ],
  "identifier": {
    "doi": "10.1016/j.ijcard.2015.11.174"
  },
  "publisher": "Elsevier BV",
  "title": "Corrigendum to “Aorta-to-arm pulse wave transit time ratio: Better prediction of coronary artery disease and stroke than pulse wave velocity” [International Journal of Cardiology 204 (2016), 1–3]"
}
