{
  "retracted": false,
  "timestamp": 1506816000000,
  "updates": [
    {
      "timestamp": 1557357092707,
      "identifier": {
        "doi": "10.1016/j.hlc.2017.08.004"
      },
      "type": "erratum"
    }
  ],
  "identifier": {
    "doi": "10.1016/j.hlc.2016.06.789"
  },
  "journal": "Heart, Lung and Circulation",
  "publisher": "Elsevier BV",
  "title": "Corrigendum to ′National Heart Foundation of Australia & Cardiac Society of Australia and New Zealand: Australian Clinical Guidelines for the Management of Acute Coronary Syndromes 2016′ Heart Lung and Circulation volume 25, (2016) 898 - 952"
}
