{
  "retracted": false,
  "timestamp": 1584230400000,
  "updates": [
    {
      "timestamp": 1591767504871,
      "identifier": {
        "doi": "10.5999/aps.2020.00402"
      },
      "type": "correction"
    }
  ],
  "identifier": {
    "doi": "10.5999/aps.2019.01305"
  },
  "journal": "Archives of Plastic Surgery",
  "publisher": "Korean Society of Plastic and Reconstructive Surgeons",
  "title": "Clinical application of cryolipolysis in Asian patients for subcutaneous fat reduction and body contouring"
}
