{
  "retracted": false,
  "timestamp": 1520985600000,
  "updates": [
    {
      "timestamp": 1574810020234,
      "identifier": {
        "doi": "10.1038/s41594-018-0044-6"
      },
      "type": "correction"
    }
  ],
  "identifier": {
    "doi": "10.1038/s41594-017-0020-6"
  },
  "journal": "Nature Structural & Molecular Biology",
  "publisher": "Springer Science and Business Media LLC",
  "title": "Author Correction: Structural basis of AAUAAA polyadenylation signal recognition by the human CPSF complex"
}
