{
  "retracted": false,
  "timestamp": 1496620800000,
  "updates": [
    {
      "timestamp": 1557357117662,
      "identifier": {
        "doi": "10.1016/j.saa.2017.02.033"
      },
      "type": "erratum"
    }
  ],
  "identifier": {
    "doi": "10.1016/j.saa.2014.09.004"
  },
  "publisher": "Elsevier BV",
  "title": "Corrigendum to “Highly selective colorimetric detection and estimation of Hg2+ at nano-molar concentration by silver nanoparticles in the presence of glutathione” [Spectrochim. Acta A Mol. Biomol. Spectrosc. 137 (2015) 503–508]"
}
