{
  "retracted": false,
  "timestamp": 1559260800000,
  "updates": [
    {
      "timestamp": 1561626668952,
      "identifier": {
        "doi": "10.1007/s00253-019-09924-7"
      },
      "type": "correction"
    }
  ],
  "identifier": {
    "doi": "10.1007/s00253-018-9376-8"
  },
  "journal": "Applied Microbiology and Biotechnology",
  "publisher": "Springer Science and Business Media LLC",
  "title": "Correction to: Phloretin reduces cell injury and inflammation mediated by Staphylococcus aureus via targeting sortase B and the molecular mechanism"
}
