{
  "retracted": false,
  "timestamp": 1538352000000,
  "updates": [
    {
      "timestamp": 1550511863777,
      "identifier": {
        "doi": "10.1371/journal.pone.0205302"
      },
      "type": "correction"
    }
  ],
  "identifier": {
    "doi": "10.1371/journal.pone.0194189"
  },
  "journal": "PLOS ONE",
  "publisher": "Public Library of Science (PLoS)",
  "title": "Correction: Disrupted dispersal and its genetic consequences: Comparing protected and threatened baboon populations (Papio papio) in West Africa"
}
