{
  "retracted": false,
  "timestamp": 1526601600000,
  "updates": [
    {
      "timestamp": 1574815597963,
      "identifier": {
        "doi": "10.1016/j.enggeo.2018.03.006"
      },
      "type": "erratum"
    }
  ],
  "identifier": {
    "doi": "10.1016/j.enggeo.2017.08.011"
  },
  "journal": "Engineering Geology",
  "publisher": "Elsevier BV",
  "title": "Corrigendum to “The effects of nearby fractures on hydraulically induced fracture propagation and permeability changes”[Eng. Geol. 228 (2017) 197–213]"
}
