{
  "retracted": false,
  "timestamp": 1522886400000,
  "updates": [
    {
      "timestamp": 1574818846610,
      "identifier": {
        "doi": "10.1038/s41598-018-23581-2"
      },
      "type": "correction"
    }
  ],
  "identifier": {
    "doi": "10.1038/s41598-017-02323-w"
  },
  "journal": "Scientific Reports",
  "publisher": "Springer Science and Business Media LLC",
  "title": "Author Correction: Limited evidence on the effectiveness of interventions to reduce livestock predation by large carnivores"
}
