{
  "retracted": false,
  "timestamp": 1525392000000,
  "updates": [
    {
      "timestamp": 1574830461319,
      "identifier": {
        "doi": "10.1038/s41467-018-04181-0"
      },
      "type": "correction"
    }
  ],
  "identifier": {
    "doi": "10.1038/s41467-017-02143-6"
  },
  "journal": "Nature Communications",
  "publisher": "Springer Science and Business Media LLC",
  "title": "Author Correction: Floats with bio-optical sensors reveal what processes trigger the North Atlantic bloom"
}
