{
  "retracted": false,
  "timestamp": 1453334400000,
  "updates": [
    {
      "timestamp": 1588990335418,
      "identifier": {
        "doi": "10.1371/journal.pone.0147656"
      },
      "type": "correction"
    }
  ],
  "identifier": {
    "doi": "10.1371/journal.pone.0140217"
  },
  "publisher": "Public Library of Science (PLoS)",
  "title": "Correction: How Many Political Parties Should Brazil Have? A Data-Driven Method to Assess and Reduce Fragmentation in Multi-Party Political Systems"
}
