{
  "retracted": true,
  "timestamp": 1589846400000,
  "updates": [
    {
      "timestamp": 1589884851238,
      "identifier": {
        "doi": "10.1186/s40543-020-00215-9"
      },
      "type": "retraction"
    }
  ],
  "identifier": {
    "doi": "10.1186/s40543-016-0099-0"
  },
  "journal": "Journal of Analytical Science and Technology",
  "publisher": "Springer Science and Business Media LLC",
  "title": "Retraction Note: Method development, validation, and stability studies of teneligliptin by RP-HPLC and identification of degradation products by UPLC tandem mass spectroscopy"
}
