{
  "retracted": false,
  "timestamp": 1191196800000,
  "updates": [
    {
      "timestamp": 1586842822347,
      "identifier": {
        "doi": "10.1128/aem.01548-07"
      },
      "type": "correction"
    }
  ],
  "identifier": {
    "doi": "10.1128/aem.00222-07"
  },
  "journal": "Applied and Environmental Microbiology",
  "publisher": "American Society for Microbiology",
  "title": "Molecular Identification and Genetic Analysis of Norovirus Genogroups I and II in Water Environments: Comparative Analysis of Different Reverse Transcription-PCR Assays"
}
