{
  "retracted": false,
  "timestamp": 1563148800000,
  "updates": [
    {
      "timestamp": 1585242070482,
      "identifier": {
        "doi": "10.1186/s13054-019-2536-0"
      },
      "type": "correction"
    }
  ],
  "identifier": {
    "doi": "10.1186/s13054-019-2329-5"
  },
  "publisher": "Springer Science and Business Media LLC",
  "title": "Correction to: The early identification of disease progression in patients with suspected infection presenting to the emergency department: a multi-centre derivation and validation study"
}
