{
  "retracted": false,
  "timestamp": 1433116800000,
  "updates": [
    {
      "timestamp": 1586572360711,
      "identifier": {
        "doi": "10.1016/j.euroneuro.2015.05.001"
      },
      "type": "erratum"
    }
  ],
  "identifier": {
    "doi": "10.1016/j.euroneuro.2013.11.012"
  },
  "publisher": "Elsevier BV",
  "title": "Corrigendum to “Effects of raloxifene on cognition in postmenopausal women with schizophrenia: Adouble-blind, randomized, placebo-controlled trial” [Eur. Neuropsychopharmacol. 24 (2014) 223–231]"
}
