{
  "retracted": false,
  "timestamp": 1555891200000,
  "updates": [
    {
      "timestamp": 1558559561980,
      "identifier": {
        "doi": "10.1007/s11356-019-05113-1"
      },
      "type": "correction"
    }
  ],
  "identifier": {
    "doi": "10.1007/s11356-019-04697-y"
  },
  "journal": "Environmental Science and Pollution Research",
  "publisher": "Springer Science and Business Media LLC",
  "title": "Correction to: Study on habitat suitability of overwintering cranes based on landscape pattern change—a case study of typical lake wetlands in the middle and lower reaches of the Yangtze River"
}
