{
  "retracted": false,
  "timestamp": 1536105600000,
  "updates": [
    {
      "timestamp": 1567640475559,
      "identifier": {
        "doi": "10.1007/s00256-018-3054-x"
      },
      "type": "correction"
    }
  ],
  "identifier": {
    "doi": "10.1007/s00256-016-2533-1"
  },
  "journal": "Skeletal Radiology",
  "publisher": "Springer Science and Business Media LLC",
  "title": "Correction to: Osteitis: a retrospective feasibility study comparing single-source dual-energy CT to MRI in selected patients with suspected acute gout"
}
