{
  "retracted": false,
  "timestamp": 1230768000000,
  "updates": [
    {
      "timestamp": 1586275868403,
      "identifier": {
        "doi": "10.1128/aac.01442-08"
      },
      "type": "correction"
    }
  ],
  "identifier": {
    "doi": "10.1128/aac.00622-08"
  },
  "journal": "Antimicrobial Agents and Chemotherapy",
  "publisher": "American Society for Microbiology",
  "title": "Prevalence and Mechanisms of Broad-Spectrum β-Lactam Resistance in Enterobacteriaceae: a Children's Hospital Experience"
}
