{
  "retracted": true,
  "timestamp": 1588291200000,
  "updates": [
    {
      "timestamp": 1591789250260,
      "identifier": {
        "doi": "10.3390/insects11060360"
      },
      "type": "retraction"
    }
  ],
  "identifier": {
    "doi": "10.3390/insects11050276"
  },
  "journal": "Insects",
  "publisher": "MDPI AG",
  "title": "Retraction: Al-Behadili, F.J.M., et al. Cold Responses of the Mediterranean Fruit Fly Ceratitis capitata Wiedemann (Diptera: Tephritidae) in Blueberry. Insects 2020, 11, 276"
}
