{
  "retracted": false,
  "timestamp": 1590192000000,
  "updates": [
    {
      "timestamp": 1590234043134,
      "identifier": {
        "doi": "10.1007/s00431-020-03692-7"
      },
      "type": "correction"
    }
  ],
  "identifier": {
    "doi": "10.1007/s00431-019-03545-y"
  },
  "journal": "European Journal of Pediatrics",
  "publisher": "Springer Science and Business Media LLC",
  "title": "Correction to: The pitfalls and promise of liquid biopsies for diagnosing and treating solid tumors in children: as review"
}
