{
  "retracted": false,
  "timestamp": 1348704000000,
  "updates": [
    {
      "timestamp": 1579178410219,
      "identifier": {
        "doi": "10.1007/978-1-62703-155-4_25"
      },
      "type": "erratum"
    }
  ],
  "identifier": {
    "doi": "10.1007/978-1-62703-155-4_12"
  },
  "journal": "Peroxisome Proliferator-Activated Receptors (PPARs)",
  "publisher": "Humana Press",
  "title": "In Vivo Studies of PPAR-Chromatin Interactions: Chromatin Immunoprecipitation for Single-Locus and Genomewide Analyses"
}
