{
  "retracted": false,
  "timestamp": 1560556800000,
  "updates": [
    {
      "timestamp": 1586905024300,
      "identifier": {
        "doi": "10.1016/j.jad.2019.03.081"
      },
      "type": "erratum"
    }
  ],
  "identifier": {
    "doi": "10.1016/j.jad.2018.11.085"
  },
  "publisher": "Elsevier BV",
  "title": "Corrigendum to “Altered white matter volumes in first-episode depression: Evidence from cross-sectional and longitudinal voxel-based analyses” Journal of Affective Disorders 245 (2019) 971–977"
}
