{
  "retracted": false,
  "timestamp": 1446681600000,
  "updates": [
    {
      "timestamp": 1574170805230,
      "identifier": {
        "doi": "10.1182/blood-2015-09-671396"
      },
      "type": "erratum"
    }
  ],
  "identifier": {
    "doi": "10.1182/blood-2014-11-611905"
  },
  "journal": "Blood",
  "publisher": "American Society of Hematology",
  "title": "Lorenz V, Stegner D, Stritt S, et al. Targeted downregulation of platelet CLEC-2 occurs through Syk-independent internalization. Blood. 2015;125(26):4069-4077."
}
