{
  "retracted": true,
  "timestamp": 1484092800000,
  "updates": [
    {
      "timestamp": 1550345947638,
      "identifier": {
        "doi": "10.1007/s40615-016-0330-0"
      },
      "type": "retraction"
    }
  ],
  "identifier": {
    "doi": "10.1007/s40615-016-0330-0"
  },
  "journal": "Journal of Racial and Ethnic Health Disparities",
  "publisher": "Springer Nature",
  "title": "RETRACTED ARTICLE: Summer Research Training Provides Effective Tools for Underrepresented Minorities to Obtain Doctoral Level Degrees"
}
