{
  "retracted": false,
  "timestamp": 1403568000000,
  "updates": [
    {
      "timestamp": 1496048025524,
      "identifier": {
        "doi": "10.1007/s40292-014-0061-4"
      },
      "type": "correction"
    }
  ],
  "identifier": {
    "doi": "10.1007/s40292-013-0034-z"
  },
  "publisher": "Springer Nature",
  "title": "Erratum to: National Survey on Excellence Centers and Reference Centers for Hypertension Diagnosis and Treatment: Geographical Distribution, Medical Facilities and Diagnostic Opportunities"
}
