{
  "retracted": false,
  "timestamp": 1445472000000,
  "updates": [
    {
      "timestamp": 1496039935209,
      "identifier": {
        "doi": "10.1371/journal.pone.0141704"
      },
      "type": "correction"
    }
  ],
  "identifier": {
    "doi": "10.1371/journal.pone.0136324"
  },
  "journal": "PLOS ONE",
  "publisher": "Public Library of Science (PLoS)",
  "title": "Correction: Efficacy and Safety Assessment of the Addition of Bevacizumab to Adjuvant Therapy Agents in Cancer Patients: A Systematic Review and Meta-Analysis of Randomized Controlled Trials"
}
