{
  "retracted": false,
  "timestamp": 1577318400000,
  "updates": [
    {
      "timestamp": 1591710067234,
      "identifier": {
        "doi": "10.1073/pnas.1920067116"
      },
      "type": "correction"
    }
  ],
  "identifier": {
    "doi": "10.1073/pnas.1903134116"
  },
  "journal": "Proceedings of the National Academy of Sciences",
  "publisher": "Proceedings of the National Academy of Sciences",
  "title": "Correction for de la Cuesta et al., Oil and aid revenue produce equal demands for accountability as taxes in Ghana and Uganda"
}
