{
  "retracted": false,
  "timestamp": 1528156800000,
  "updates": [
    {
      "timestamp": 1574840274885,
      "identifier": {
        "doi": "10.1073/pnas.1808125115"
      },
      "type": "correction"
    }
  ],
  "identifier": {
    "doi": "10.1073/pnas.1717873115"
  },
  "journal": "Proceedings of the National Academy of Sciences",
  "publisher": "Proceedings of the National Academy of Sciences",
  "title": "Correction for Ponce de León et al., Human bony labyrinth is an indicator of population history and dispersal from Africa"
}
