{
  "retracted": false,
  "timestamp": 1576713600000,
  "updates": [
    {
      "timestamp": 1591712316998,
      "identifier": {
        "doi": "10.1186/s12879-019-4698-4"
      },
      "type": "correction"
    }
  ],
  "identifier": {
    "doi": "10.1186/s12879-019-4634-7"
  },
  "journal": "BMC Infectious Diseases",
  "publisher": "Springer Science and Business Media LLC",
  "title": "Correction to: Clinical diversity of invasive cryptococcosis in AIDS patients from central China: report of two cases with review of literature"
}
