{
  "retracted": false,
  "timestamp": 1579651200000,
  "updates": [
    {
      "timestamp": 1591731617665,
      "identifier": {
        "doi": "10.1007/s13562-019-00547-7"
      },
      "type": "correction"
    }
  ],
  "identifier": {
    "doi": "10.1007/s13562-019-00541-z"
  },
  "journal": "Journal of Plant Biochemistry and Biotechnology",
  "publisher": "Springer Science and Business Media LLC",
  "title": "Correction to: Transcriptome analysis of flowering genes in mango (Mangifera indica L.) in relation to floral malformation"
}
