{
  "retracted": false,
  "timestamp": 1504656000000,
  "updates": [
    {
      "timestamp": 1550490335445,
      "identifier": {
        "doi": "10.1371/journal.pone.0184609"
      },
      "type": "correction"
    }
  ],
  "identifier": {
    "doi": "10.1371/journal.pone.0172127"
  },
  "journal": "PLOS ONE",
  "publisher": "Public Library of Science (PLoS)",
  "title": "Correction: Evaluation of different mathematical models and different b-value ranges of diffusion-weighted imaging in peripheral zone prostate cancer detection using b-value up to 4500 s/mm2"
}
