{
  "retracted": false,
  "timestamp": 1515628800000,
  "updates": [
    {
      "timestamp": 1557319314673,
      "identifier": {
        "doi": "10.1016/j.ijhydene.2017.11.146"
      },
      "type": "erratum"
    }
  ],
  "identifier": {
    "doi": "10.1016/j.ijhydene.2016.06.163"
  },
  "journal": "International Journal of Hydrogen Energy",
  "publisher": "Elsevier BV",
  "title": "Corrigendum to “Performances analysis of WT-DFIG with PV and fuel cell hybrid power sources system associated with hydrogen storage hybrid energy system” [Int J Hydrogen Energy 41 (2016) 21006–21021]"
}
