{
  "retracted": false,
  "timestamp": 1568937600000,
  "updates": [
    {
      "timestamp": 1572514847947,
      "identifier": {
        "doi": "10.1007/s10971-019-05126-9"
      },
      "type": "correction"
    }
  ],
  "identifier": {
    "doi": "10.1007/s10971-019-05102-3"
  },
  "journal": "Journal of Sol-Gel Science and Technology",
  "publisher": "Springer Science and Business Media LLC",
  "title": "Correction to: The effect of partial substitution of Pd in LaMnO3 polycrystalline materials synthesized by sol–gel technique on the electrical performance"
}
