{
  "retracted": false,
  "timestamp": 1496275200000,
  "updates": [
    {
      "timestamp": 1550452446703,
      "identifier": {
        "doi": "10.1161/str.0000000000000135"
      },
      "type": "correction"
    }
  ],
  "identifier": {
    "doi": "10.1161/strokeaha.116.016149"
  },
  "publisher": "Ovid Technologies (Wolters Kluwer Health)",
  "title": "Correction to: Predictors of the Aspiration Component Success of a Direct Aspiration First Pass Technique (ADAPT) for the Endovascular Treatment of Stroke Reperfusion Strategy in Anterior Circulation Acute Stroke"
}
