{
  "retracted": false,
  "timestamp": 1522540800000,
  "updates": [
    {
      "timestamp": 1574811039722,
      "identifier": {
        "doi": "10.1016/j.ijrobp.2017.12.271"
      },
      "type": "erratum"
    }
  ],
  "identifier": {
    "doi": "10.1016/j.ijrobp.2017.06.2449"
  },
  "journal": "International Journal of Radiation Oncology*Biology*Physics",
  "publisher": "Elsevier BV",
  "title": "Erratum to: Mahmood J, Connors CQ, Alexander AA, et al. Cavernous nerve injury by radiation therapy may potentiate erectile dysfunction in rats. Int J Radiat Oncol Biol Phys 2017;99:680-688."
}
