{
  "retracted": false,
  "timestamp": 1548979200000,
  "updates": [
    {
      "timestamp": 1560526989124,
      "identifier": {
        "doi": "10.1016/j.bioelechem.2018.07.012"
      },
      "type": "erratum"
    }
  ],
  "identifier": {
    "doi": "10.1016/j.bioelechem.2017.12.006"
  },
  "journal": "Bioelectrochemistry",
  "publisher": "Elsevier BV",
  "title": "Corrigendum to “Reductive electrografting of in situ produced diazopyridinium cations: Tailoring the interface between carbon electrodes and electroactive bacterial films” [Bioelectrochem. 120 (2018) 157–165]"
}
