{
  "retracted": false,
  "timestamp": 1547078400000,
  "updates": [
    {
      "timestamp": 1586885328082,
      "identifier": {
        "doi": "10.1080/08039488.2018.1540324"
      },
      "type": "correction"
    }
  ],
  "identifier": {
    "doi": "10.1080/08039488.2018.1465592"
  },
  "publisher": "Informa UK Limited",
  "title": "Correction to: P. Bech and N. Timmerby, An overview of which health domains to consider and when to apply them in measurement-based care for depression and anxiety disorders"
}
