{
  "retracted": false,
  "timestamp": 1496275200000,
  "updates": [
    {
      "timestamp": 1495728767542,
      "identifier": {
        "doi": "10.1016/j.envpol.2017.03.003"
      },
      "type": "erratum"
    }
  ],
  "identifier": {
    "doi": "10.1016/j.envpol.2016.04.032"
  },
  "publisher": "Elsevier BV",
  "title": "Corrigendum to “Supplementary material – Traceability of fluorescent engineered nanomaterials and their fate in complex liquid waste matrices” [Environ. Pollut. 214 (July 2016), 795–805]"
}
