{
  "retracted": false,
  "timestamp": 1506038400000,
  "updates": [
    {
      "timestamp": 1585463316698,
      "identifier": {
        "doi": "10.1007/s00467-017-3792-3"
      },
      "type": "erratum"
    }
  ],
  "identifier": {
    "doi": "10.1007/s00467-017-3720-6"
  },
  "publisher": "Springer Science and Business Media LLC",
  "title": "Erratum to: Evaluation of the safety and efficacy of metoprolol infusion for children and adolescents with hypertensive crises: a retrospective case series"
}
