{
  "retracted": false,
  "timestamp": 1507766400000,
  "updates": [
    {
      "timestamp": 1553020973410,
      "identifier": {
        "doi": "10.1007/s10209-017-0574-4"
      },
      "type": "correction"
    }
  ],
  "identifier": {
    "doi": "10.1007/s10209-017-0570-8"
  },
  "journal": "Universal Access in the Information Society",
  "publisher": "Springer Nature",
  "title": "Correction to: A review of assistive spatial orientation and navigation technologies for the visually impaired"
}
