{
  "retracted": false,
  "timestamp": 1451606400000,
  "updates": [
    {
      "timestamp": 1496038566375,
      "identifier": {
        "doi": "10.1016/j.optcom.2015.10.003"
      },
      "type": "err"
    }
  ],
  "identifier": {
    "doi": "10.1016/j.optcom.2009.08.003"
  },
  "journal": "Optics Communications",
  "publisher": "Elsevier BV",
  "title": "Corrigendum to “An inhomogeneous theoretical model for analysis of PbSe quantum-dot-doped fiber amplifier” [Opt. Commun. 282 (22) (2009) 4449–4454]"
}
