{
  "retracted": false,
  "timestamp": 1575849600000,
  "updates": [
    {
      "timestamp": 1591696520059,
      "identifier": {
        "doi": "10.36959/422/433"
      },
      "type": "correction"
    }
  ],
  "identifier": {
    "doi": "10.36959/422/433"
  },
  "journal": "Journal of Aerospace Engineering and Mechanics",
  "publisher": "sPage.direcT",
  "title": "Low-Cycle-Fatigue Failures of Solder Material in Electronics Packaging: Analytical Modeling Enables to Predict and Possibly Prevent Them-Review"
}
