{
  "retracted": false,
  "timestamp": 1536796800000,
  "updates": [
    {
      "timestamp": 1588999748792,
      "identifier": {
        "doi": "10.1371/journal.pone.0204198"
      },
      "type": "correction"
    }
  ],
  "identifier": {
    "doi": "10.1371/journal.pone.0188551"
  },
  "publisher": "Public Library of Science (PLoS)",
  "title": "Correction: Improvement in cardiac dysfunction with a novel circuit training method combining simultaneous aerobic-resistance exercises. A randomized trial"
}
