{
  "retracted": false,
  "timestamp": 1378771200000,
  "updates": [
    {
      "timestamp": 1496053923220,
      "identifier": {
        "doi": "10.1371/annotation/99966397-acf2-41ca-ad92-69dbd87cc9f9"
      },
      "type": "correction"
    }
  ],
  "identifier": {
    "doi": "10.1371/journal.pone.0066111"
  },
  "journal": "PLoS ONE",
  "publisher": "Public Library of Science (PLoS)",
  "title": "Correction: Differential Regulation of MAPK Phosphorylation in the Dorsal Hippocampus in Response to Prolonged Morphine Withdrawal-Induced Depressive-Like Symptoms in Mice"
}
