{
  "retracted": false,
  "timestamp": 1409270400000,
  "updates": [
    {
      "timestamp": 1589388215063,
      "identifier": {
        "doi": "10.1128/mbio.01575-14"
      },
      "type": "correction"
    }
  ],
  "identifier": {
    "doi": "10.1128/mbio.01241-14"
  },
  "publisher": "American Society for Microbiology",
  "title": "Erratum for Yeruva et al., Early MicroRNA Expression Profile as a Prognostic Biomarker for the Development of Pelvic Inflammatory Disease in a Mouse Model of Chlamydial Genital Infection"
}
