{
  "retracted": false,
  "timestamp": 1446336000000,
  "updates": [
    {
      "timestamp": 1496014993884,
      "identifier": {
        "doi": "10.1016/j.gmit.2015.06.004"
      },
      "type": "err"
    }
  ],
  "identifier": {
    "doi": "10.1016/j.gmit.2014.05.008"
  },
  "journal": "Gynecology and Minimally Invasive Therapy",
  "publisher": "Elsevier BV",
  "title": "Corrigendum to “Laparoscopic subtotal hysterectomy in the era of minimally invasive surgery” [Gynecol Minim Invasive Ther 4 (2015) 8–13]"
}
