{
  "retracted": false,
  "timestamp": 1589500800000,
  "updates": [
    {
      "timestamp": 1590770663511,
      "identifier": {
        "doi": "10.1038/s41379-020-0570-8"
      },
      "type": "correction"
    }
  ],
  "identifier": {
    "doi": "10.1038/s41379-020-0542-z"
  },
  "journal": "Modern Pathology",
  "publisher": "Springer Science and Business Media LLC",
  "title": "Correction: NFATc2-rearranged sarcomas: clinicopathologic, molecular, and cytogenetic study of 7 cases with evidence of AGGRECAN as a novel diagnostic marker"
}
