{
  "retracted": false,
  "timestamp": 1590105600000,
  "updates": [
    {
      "timestamp": 1590176451179,
      "identifier": {
        "doi": "10.2514/6.2020-0667.c1"
      },
      "type": "correction"
    }
  ],
  "identifier": {
    "doi": "10.2514/6.2020-0667"
  },
  "journal": "AIAA Scitech 2020 Forum",
  "publisher": "American Institute of Aeronautics and Astronautics",
  "title": "Correction: Design and Evaluation of a Constraint-Based Head-Up Display for Helicopter Obstacle Avoidance During Forward Flight"
}
