{
  "retracted": false,
  "timestamp": 1588723200000,
  "updates": [
    {
      "timestamp": 1590500611685,
      "identifier": {
        "doi": "10.1038/s41575-020-0311-y"
      },
      "type": "correction"
    }
  ],
  "identifier": {
    "doi": "10.1038/s41575-020-0294-8"
  },
  "journal": "Nature Reviews Gastroenterology & Hepatology",
  "publisher": "Springer Science and Business Media LLC",
  "title": "Author Correction: Management of IBD during the COVID-19 outbreak: resetting clinical priorities"
}
