{
  "retracted": false,
  "timestamp": 1489795200000,
  "updates": [
    {
      "timestamp": 1585384077438,
      "identifier": {
        "doi": "10.1007/s12187-017-9465-8"
      },
      "type": "erratum"
    }
  ],
  "identifier": {
    "doi": "10.1007/s12187-015-9323-5"
  },
  "publisher": "Springer Science and Business Media LLC",
  "title": "Erratum to: The Current Evidence Base and Future Needs in Improving Children’s Well-Being Across Europe: is There a Case for a Comparative Longitudinal Survey?"
}
