{
  "retracted": false,
  "timestamp": 1519862400000,
  "updates": [
    {
      "timestamp": 1585473312480,
      "identifier": {
        "doi": "10.1016/j.archger.2017.10.004"
      },
      "type": "erratum"
    }
  ],
  "identifier": {
    "doi": "10.1016/j.archger.2017.07.021"
  },
  "publisher": "Elsevier BV",
  "title": "Corrigendum to “Association between joint stiffness and health-related quality of life in community-dwelling older adults” [Arch. Gerontol. Geriatr. 73 (November 2017) 234–239]"
}
