{
  "retracted": false,
  "timestamp": 833587200000,
  "updates": [
    {
      "timestamp": 1580256619858,
      "identifier": {
        "doi": "10.1084/jem.183.6.2705"
      },
      "type": "correction"
    }
  ],
  "identifier": {
    "doi": "10.1084/jem.182.2.305"
  },
  "journal": "The Journal of Experimental Medicine",
  "publisher": "Rockefeller University Press",
  "title": "Cloning and characterization of 5E6 (Ly-49C), a receptor molecule expressed on a subset of murine natural killer cells."
}
