{
  "retracted": false,
  "timestamp": 983404800000,
  "updates": [
    {
      "timestamp": 1591786855636,
      "identifier": {
        "doi": "10.1128/aem.67.3.1404-1404.2001"
      },
      "type": "correction"
    }
  ],
  "identifier": {
    "doi": "10.1128/aem.66.12.5540-5543.2000"
  },
  "journal": "Applied and Environmental Microbiology",
  "publisher": "American Society for Microbiology",
  "title": "Loss of O157 O Antigenicity of Verotoxin-ProducingEscherichia coli O157:H7 Surviving under Starvation Conditions"
}
